pipeline_runner/__init__.py
pipeline_runner/__main__.py
pipeline_runner/artifacts.py
pipeline_runner/cache.py
pipeline_runner/cli.py
pipeline_runner/config.py
pipeline_runner/container.py
pipeline_runner/context.py
pipeline_runner/errors.py
pipeline_runner/models.py
pipeline_runner/oidc.py
pipeline_runner/parse.py
pipeline_runner/py.typed
pipeline_runner/repository.py
pipeline_runner/runner.py
pipeline_runner/service.py
pipeline_runner/static/__init__.py
pipeline_runner/static/known_hosts
pipeline_runner/utils.py
bitbucket_pipeline_runner-0.6.0.dist-info/METADATA
bitbucket_pipeline_runner-0.6.0.dist-info/WHEEL
bitbucket_pipeline_runner-0.6.0.dist-info/entry_points.txt
bitbucket_pipeline_runner-0.6.0.dist-info/licenses/LICENSE
bitbucket_pipeline_runner-0.6.0.dist-info/RECORD
