Metadata-Version: 2.4
Name: bitbucket-pipeline-runner
Version: 0.6.0
Summary: Run a bitbucket pipeline locally
License-Expression: MIT
License-File: LICENSE
Author: Mathieu Lemay
Author-email: acidrain1@gmail.com
Requires-Python: >=3.10
Classifier: Programming Language :: Python :: 3
Classifier: Programming Language :: Python :: 3.10
Classifier: Programming Language :: Python :: 3.11
Classifier: Programming Language :: Python :: 3.12
Classifier: Programming Language :: Python :: 3.13
Classifier: Programming Language :: Python :: 3.14
Requires-Dist: boto3 (>=1.37.13,<2.0.0)
Requires-Dist: click (>=8.1.8,<9.0.0)
Requires-Dist: coloredlogs (>=15.0.1,<16.0.0)
Requires-Dist: cryptography (>=46.0.3,<47.0.0)
Requires-Dist: docker (>=7.1.0,<8.0.0)
Requires-Dist: gitpython (>=3.1.44,<4.0.0)
Requires-Dist: platformdirs (>=4.3.6,<5.0.0)
Requires-Dist: pydantic (>=2.10.6,<3.0.0)
Requires-Dist: pydantic-settings (>=2.8.1,<3.0.0)
Requires-Dist: pyfzf (>=0.3.1,<0.4.0)
Requires-Dist: pyjwt (>=2.10.1,<3.0.0)
Requires-Dist: python-dotenv (>=1.0.1,<2.0.0)
Requires-Dist: python-slugify (>=8.0.4,<9.0.0)
Requires-Dist: pyyaml (>=6.0.2,<7.0.0)
Requires-Dist: requests (>=2.32.3,<3.0.0)
Requires-Dist: tenacity (>=9.0.0,<10.0.0)
Project-URL: Repository, https://github.com/mathieu-lemay/pipeline-runner
